twined/__init__.py
twined/exceptions.py
twined/migrations/__init__.py
twined/schema/__init__.py
twined/schema/plotly_schema.json
twined/schema/twine_schema.json
twined/twine.py
twined/utils/__init__.py
twined/utils/encoders.py
twined/utils/load_json.py
twined/utils/strings.py
twined-0.7.0.dist-info/LICENSE
twined-0.7.0.dist-info/METADATA
twined-0.7.0.dist-info/WHEEL
twined-0.7.0.dist-info/RECORD
