Metadata-Version: 2.3
Name: twined
Version: 0.7.0
Summary: A library to help digital twins and data services talk to one another.
License: MIT
Keywords: digital,twins,data,services,python,schema
Author: Octue (github: octue)
Author-email: support@octue.com
Requires-Python: >=3.10,<4.0
Classifier: Development Status :: 4 - Beta
Classifier: Intended Audience :: Developers
Classifier: License :: OSI Approved :: MIT License
Classifier: Operating System :: OS Independent
Classifier: Programming Language :: Python :: 3
Classifier: Programming Language :: Python :: 3.10
Classifier: Programming Language :: Python :: 3.11
Classifier: Programming Language :: Python :: 3.12
Classifier: Programming Language :: Python :: 3.13
Classifier: Topic :: Software Development :: Libraries :: Python Modules
Requires-Dist: jsonschema (>=4,<5)
Requires-Dist: python-dotenv (>=0,<=2)
Project-URL: Repository, https://www.github.com/octue/twined
